main.py
mseep_zeropath_mcp_server-0.1.4.dist-info/METADATA
mseep_zeropath_mcp_server-0.1.4.dist-info/WHEEL
mseep_zeropath_mcp_server-0.1.4.dist-info/entry_points.txt
mseep_zeropath_mcp_server-0.1.4.dist-info/top_level.txt
mseep_zeropath_mcp_server-0.1.4.dist-info/RECORD
