Metadata-Version: 2.4
Name: mseep-zeropath-mcp-server
Version: 0.1.4
Summary: Add your description here
Author-email: mseep <support@skydeck.ai>
Requires-Python: >=3.12
Requires-Dist: mcp[cli]>=1.5.0
Requires-Dist: requests>=2.32.3
